zkyutils/__init__.py
zkyutils/excel.py
zkyutils/inputs.py
zkyutils/logger.py
zkyutils/request.py
zkyutils/utils.py
zkyutils-1.0.18.dist-info/LICENSE
zkyutils-1.0.18.dist-info/METADATA
zkyutils-1.0.18.dist-info/WHEEL
zkyutils-1.0.18.dist-info/top_level.txt
zkyutils-1.0.18.dist-info/RECORD
